{
    "_links": {
        "self": {
            "href": "http:\/\/default\/sites\/default\/files\/media\/image\/banner-160217-6148.jpg"
        },
        "type": {
            "href": "http:\/\/drupal.org\/rest\/type\/file\/file"
        },
        "http:\/\/drupal.org\/rest\/relation\/file\/file\/uid": [
            {
                "href": "http:\/\/default\/user\/1?_format=hal_json"
            }
        ]
    },
    "uuid": [
        {
            "value": "34afd658-d8f1-4ef4-99cb-06dd96b64dc1"
        }
    ],
    "langcode": [
        {
            "value": "en"
        }
    ],
    "_embedded": {
        "http:\/\/drupal.org\/rest\/relation\/file\/file\/uid": [
            {
                "_links": {
                    "self": {
                        "href": "http:\/\/default\/user\/1?_format=hal_json"
                    },
                    "type": {
                        "href": "http:\/\/drupal.org\/rest\/type\/user\/user"
                    }
                },
                "uuid": [
                    {
                        "value": "fda67224-1251-4c7c-bad0-9c1f244e53f9"
                    }
                ]
            }
        ]
    },
    "filename": [
        {
            "value": "banner-160217-6148.jpg"
        }
    ],
    "uri": [
        {
            "value": "public:\/\/media\/image\/banner-160217-6148.jpg",
            "url": "\/sites\/default\/files\/media\/image\/banner-160217-6148.jpg"
        }
    ],
    "filemime": [
        {
            "value": "image\/jpeg"
        }
    ],
    "filesize": [
        {
            "value": 369276
        }
    ],
    "status": [
        {
            "value": true
        }
    ],
    "created": [
        {
            "value": "2020-02-13T23:14:19+00:00",
            "format": "Y-m-d\\TH:i:sP"
        }
    ],
    "changed": [
        {
            "value": "2020-02-13T23:14:19+00:00",
            "format": "Y-m-d\\TH:i:sP"
        }
    ]
}
